portscanner/__init__.py
portscanner/__main__.py
portscanner/colors.py
portscanner/mixins/__init__.py
portscanner/mixins/loop.py
portscanner/mixins/resolver.py
portscanner/mixins/workpool.py
portscanner/parsing.py
portscanner/scanner.py
portscanner/types.py
portscanner/utils.py
portscanner-0.7.0.dist-info/entry_points.txt
portscanner-0.7.0.dist-info/licenses/LICENSE
portscanner-0.7.0.dist-info/METADATA
portscanner-0.7.0.dist-info/WHEEL
portscanner-0.7.0.dist-info/RECORD
