Metadata-Version: 2.4
Name: portscanner
Version: 0.7.0
Summary: Asynchronous Port Scanner
License-File: LICENSE
Author: GoodiesHQ
Author-email: aarcher73k@gmail.com
Requires-Python: >=3.10,<4.0
Classifier: Programming Language :: Python :: 3
Classifier: Programming Language :: Python :: 3.10
Classifier: Programming Language :: Python :: 3.11
Classifier: Programming Language :: Python :: 3.12
Classifier: Programming Language :: Python :: 3.13
Classifier: Programming Language :: Python :: 3.14
Requires-Dist: aiodns (>=3.6,<4.0)
Requires-Dist: colorama (>=0.4.6,<1.0)
